mipc_camera_client/__init__.py
mipc_camera_client/cli.py
mipc_camera_client/crypto_helpers.py
mipc_camera_client_test-0.1.4.dev0.dist-info/LICENSE
mipc_camera_client_test-0.1.4.dev0.dist-info/METADATA
mipc_camera_client_test-0.1.4.dev0.dist-info/WHEEL
mipc_camera_client_test-0.1.4.dev0.dist-info/entry_points.txt
mipc_camera_client_test-0.1.4.dev0.dist-info/RECORD
