Metadata-Version: 2.3
Name: mipc-camera-client-test
Version: 0.1.4.dev0
Summary: command-line interface and client library for MIPC IP cameras
License: BSD-3-Clause
Keywords: webcam,mipc,rtsp,ip camera,cli,command line interface,ptz
Author: Pan Maruda
Author-email: panmaruda@protonmail.com
Requires-Python: >=3.10,<4.0
Classifier: Development Status :: 4 - Beta
Classifier: Environment :: Console
Classifier: Intended Audience :: Developers
Classifier: Intended Audience :: End Users/Desktop
Classifier: License :: OSI Approved :: BSD License
Classifier: Natural Language :: English
Classifier: Programming Language :: Python :: 3
Classifier: Programming Language :: Python :: 3.10
Classifier: Programming Language :: Python :: 3.11
Classifier: Programming Language :: Python :: 3.12
Classifier: Programming Language :: Python :: 3.13
Classifier: Programming Language :: Python :: 3.9
Classifier: Topic :: Multimedia :: Video
Classifier: Topic :: Software Development :: Libraries :: Python Modules
Classifier: Topic :: Utilities
Requires-Dist: json5 (>=0.9.14,<0.10.0)
Requires-Dist: pycryptodome (>=3.18.0,<4.0.0)
Requires-Dist: requests (>=2.31.0,<3.0.0)
Project-URL: Homepage, https://github.com/pan-maruda/mipc-camera-client-python
